groovy_parser/__init__.py
groovy_parser/lexer.py
groovy_parser/parser.py
groovy_parser/py.typed
groovy_parser/tokenizer.py
groovy_parser/GROOVY_3_0_X/master_groovy_parser.g
groovy_parser-0.2.2.data/scripts/cached-translated-groovy3-parser.py
groovy_parser-0.2.2.data/scripts/translated-groovy3-parser.py
groovy_parser-0.2.2.dist-info/licenses/LICENSE
groovy_parser-0.2.2.dist-info/METADATA
groovy_parser-0.2.2.dist-info/WHEEL
groovy_parser-0.2.2.dist-info/top_level.txt
groovy_parser-0.2.2.dist-info/RECORD
