Metadata-Version: 2.4
Name: groovy-parser
Version: 0.2.2
Summary: Groovy 3.0.x parser based on Pygments and Lark
Home-page: https://github.com/inab/python-groovy-parser
Author: José M. Fernández <https://orcid.org/0000-0002-4806-5140>
Author-email: jose.m.fernandez@bsc.es
License: Apache-2.0
Project-URL: Bug Tracker, https://github.com/inab/python-groovy-parser/issues
Classifier: Programming Language :: Python :: 3
Classifier: Development Status :: 3 - Alpha
Classifier: License :: OSI Approved :: Apache Software License
Classifier: Operating System :: OS Independent
Requires-Python: >=3.7
License-File: LICENSE
Requires-Dist: lark!=1.3.0
Requires-Dist: lark<1.2.0; python_version < "3.8"
Requires-Dist: Pygments
Dynamic: author
Dynamic: author-email
Dynamic: classifier
Dynamic: description
Dynamic: description-content-type
Dynamic: home-page
Dynamic: license
Dynamic: license-file
Dynamic: project-url
Dynamic: requires-dist
Dynamic: requires-python
Dynamic: summary
